README.md
setup.py
jingyun_cli/__init__.py
jingyun_cli.egg-info/PKG-INFO
jingyun_cli.egg-info/SOURCES.txt
jingyun_cli.egg-info/dependency_links.txt
jingyun_cli.egg-info/entry_points.txt
jingyun_cli.egg-info/requires.txt
jingyun_cli.egg-info/top_level.txt
jingyun_cli/conf/__init__.py
jingyun_cli/conf/cli.py
jingyun_cli/conf/help.py
jingyun_cli/docker/__init__.py
jingyun_cli/docker/clear.py
jingyun_cli/docker/help.py
jingyun_cli/docker/jy_compose.py
jingyun_cli/jingd/__init__.py
jingyun_cli/jingd/cli.py
jingyun_cli/jingd/help.py
jingyun_cli/jingd/jy_supervisor.py
jingyun_cli/jingd/sample.py
jingyun_cli/jingd/user.py
jingyun_cli/json/__init__.py
jingyun_cli/json/cli.py
jingyun_cli/json/help.py
jingyun_cli/key/__init__.py
jingyun_cli/key/cli.py
jingyun_cli/key/help.py
jingyun_cli/oss/__init__.py
jingyun_cli/oss/cli.py
jingyun_cli/oss/help.py
jingyun_cli/server/__init__.py
jingyun_cli/server/find_port.py
jingyun_cli/server/help.py
jingyun_cli/server/ip.py
jingyun_cli/sql/__init__.py
jingyun_cli/sql/cli.py
jingyun_cli/sql/help.py
jingyun_cli/ssh/__init__.py
jingyun_cli/ssh/cli.py
jingyun_cli/ssh/help.py
jingyun_cli/util/__init__.py
jingyun_cli/util/cli_args.py
jingyun_cli/util/env.py
jingyun_cli/util/help.py
jingyun_cli/util/host.py
jingyun_cli/util/port.py
jingyun_cli/conf/__init__.py
jingyun_cli/conf/cli.py
jingyun_cli/conf/help.py
jingyun_cli/docker/__init__.py
jingyun_cli/docker/clear.py
jingyun_cli/docker/help.py
jingyun_cli/docker/jy_compose.py
jingyun_cli/jingd/__init__.py
jingyun_cli/jingd/cli.py
jingyun_cli/jingd/help.py
jingyun_cli/jingd/jy_supervisor.py
jingyun_cli/jingd/sample.py
jingyun_cli/jingd/user.py
jingyun_cli/json/__init__.py
jingyun_cli/json/cli.py
jingyun_cli/json/help.py
jingyun_cli/key/__init__.py
jingyun_cli/key/cli.py
jingyun_cli/key/help.py
jingyun_cli/oss/__init__.py
jingyun_cli/oss/cli.py
jingyun_cli/oss/help.py
jingyun_cli/server/__init__.py
jingyun_cli/server/find_port.py
jingyun_cli/server/help.py
jingyun_cli/server/ip.py
jingyun_cli/sql/__init__.py
jingyun_cli/sql/cli.py
jingyun_cli/sql/help.py
jingyun_cli/ssh/__init__.py
jingyun_cli/ssh/cli.py
jingyun_cli/ssh/help.py
jingyun_cli/util/__init__.py
jingyun_cli/util/cli_args.py
