Metadata-Version: 1.0
Name: jingyun-cli
Version: 0.5.7
Summary: jingyun deploy cli tools
Home-page: https://github.com/meisanggou/jingyun
Author: meisanggou
Author-email: zhouheng@gene.ac
License: MIT
Keywords: jingyun-cli
Platform: UNKNOWN
